langchain_baichuanai/__init__.py
langchain_baichuanai-0.0.1.dist-info/LICENSE
langchain_baichuanai-0.0.1.dist-info/METADATA
langchain_baichuanai-0.0.1.dist-info/WHEEL
langchain_baichuanai-0.0.1.dist-info/RECORD
