Metadata-Version: 2.1
Name: langchain-baichuanai
Version: 0.0.1
Summary: LangChain interface for baichuanai AI
Home-page: https://pypi.org/project/langchain-baichuanai
License: BSD-3-Clause
Author: Yi ZHANG
Author-email: yizhang.dev@gmail.com
Requires-Python: >=3.7,<4.0
Classifier: License :: OSI Approved :: BSD License
Classifier: Programming Language :: Python :: 3
Classifier: Programming Language :: Python :: 3.7
Classifier: Programming Language :: Python :: 3.8
Classifier: Programming Language :: Python :: 3.9
Classifier: Programming Language :: Python :: 3.10
Classifier: Programming Language :: Python :: 3.11
Classifier: Programming Language :: Python :: 3.12
Project-URL: Documentation, https://langchain-baichuanai.readthedocs.io/en/latest/
Project-URL: Repository, https://github.com/imyizhang/langchain-baichuanai
